<?xml version="1.0" encoding="UTF-8"?>
<?xml-stylesheet type="text/xsl" href="/main.xsl"?>
<b:blog xmlns="http://www.w3.org/1999/xhtml" xmlns:b="http://blog.othree.net"  xmlns:xsi="http://www.w3.org/2001/XMLSchema-instance" xsi:schemaLocation="http://blog.othree.net http://blog.othree.net/blooog.xsd">
	<b:blogTitle>O3noBLOG</b:blogTitle>
	<b:blogDescription></b:blogDescription>
	<b:entries>
		<b:entriesMeta>
			<b:listType>s</b:listType>
			<b:listData listID="000088" baseName="innocence">Innocence</b:listData>

			<b:previous>
				<b:mTitle>台灣 Firefox Party 推廣週</b:mTitle>
				<b:mDate>2004-11-09</b:mDate>
				<b:mBase>firefox-party-taiwan</b:mBase>
			</b:previous>


			<b:next>
				<b:mTitle>Firefox day</b:mTitle>
				<b:mDate>2004-11-22</b:mDate>
				<b:mBase>firefox-day</b:mBase>
			</b:next>

		</b:entriesMeta>
		<b:entry entryID="000088" baseName="innocence">
			<b:author>
				<b:authorName>othree</b:authorName>
				<b:authorEmail>othree@gmail.com</b:authorEmail>
				<b:authorUrl></b:authorUrl>
			</b:author>
			<b:datetime>
				<b:date>2004-11-21</b:date>
				<b:time>11:01:35</b:time>
			</b:datetime>
			<b:category>acg</b:category>

			<b:CommentsAccepted>0</b:CommentsAccepted>


			<b:PingsAccepted>0</b:PingsAccepted>

			<b:title>Innocence</b:title>
			<b:content>
				<b:summary>上週和朋友們一起去看了攻殻機動隊劇場版的最新作「Innocence」，果然有時候連看對話的來不及。 雖然很多人說這部已經變成押井守的攻殼，而不是士郎正宗的攻殼，不過我並不這樣認為，我一直都覺得攻殼的主題方向蠻明確的，一直都是在探討同一個問題：「當靈魂（或許該稱為意識）可以數位化後，怎樣才算是一個人？」上一部劇場版和漫畫探討的是自資訊大海中產生的自我意識，這次則是探討人偶（機械人？人造人？），只是這問題一直都不會有答案的。 劇情以外的，畫面實在是太漂亮了，不過也因此有些地方感覺接不太起來，尤其是金的房子那，我完全不知道那棟房子是怎樣和城市接起來的。...</b:summary>
				<b:mainContent><p>上週和朋友們一起去看了攻殻機動隊劇場版的最新作「Innocence」，果然有時候連看對話的來不及。</p>

<p>雖然很多人說這部已經變成押井守的攻殼，而不是士郎正宗的攻殼，不過我並不這樣認為，我一直都覺得攻殼的主題方向蠻明確的，一直都是在探討同一個問題：「當靈魂（或許該稱為意識）可以數位化後，怎樣才算是一個人？」上一部劇場版和漫畫探討的是自資訊大海中產生的自我意識，這次則是探討人偶（機械人？人造人？），只是這問題一直都不會有答案的。</p>

<p>劇情以外的，畫面實在是太漂亮了，不過也因此有些地方感覺接不太起來，尤其是金的房子那，我完全不知道那棟房子是怎樣和城市接起來的。</p></b:mainContent>
				<b:extendContent></b:extendContent>
			</b:content>
			<b:comments commentCount="4">

				<b:comment commentID="000097" entryID="000088">
					<b:author>
						<b:authorName>Eric</b:authorName>
						<b:authorEmail>eric95@gmail.com</b:authorEmail>
						<b:authorUrl>http://animadtk.org/</b:authorUrl>
					</b:author>
					<b:datetime>
						<b:date>2004-11-22</b:date>
						<b:time>03:39:28</b:time>
					</b:datetime>
					<b:content>
						<b:mainContent><p>有錯字！
應該是「攻」殼機動隊……</p>
</b:mainContent>
					</b:content>
				</b:comment>

				<b:comment commentID="000098" entryID="000088">
					<b:author>
						<b:authorName>OOO</b:authorName>
						<b:authorEmail>othree@gmail.com</b:authorEmail>
						<b:authorUrl>http://othree.net</b:authorUrl>
					</b:author>
					<b:datetime>
						<b:date>2004-11-22</b:date>
						<b:time>08:40:31</b:time>
					</b:datetime>
					<b:content>
						<b:mainContent><p>那個，我找不到我哪個「功」錯了&#8230;.orz</p>
</b:mainContent>
					</b:content>
				</b:comment>

				<b:comment commentID="000108" entryID="000088">
					<b:author>
						<b:authorName>ASAKU</b:authorName>
						<b:authorEmail></b:authorEmail>
						<b:authorUrl></b:authorUrl>
					</b:author>
					<b:datetime>
						<b:date>2004-11-25</b:date>
						<b:time>00:14:47</b:time>
					</b:datetime>
					<b:content>
						<b:mainContent><p>全錯&#8230;</p>
</b:mainContent>
					</b:content>
				</b:comment>

				<b:comment commentID="000109" entryID="000088">
					<b:author>
						<b:authorName>OOO</b:authorName>
						<b:authorEmail>othree@gmail.com</b:authorEmail>
						<b:authorUrl>http://othree.net</b:authorUrl>
					</b:author>
					<b:datetime>
						<b:date>2004-11-25</b:date>
						<b:time>00:31:16</b:time>
					</b:datetime>
					<b:content>
						<b:mainContent><p>總算看出來了&#8230;orz</p>
</b:mainContent>
					</b:content>
				</b:comment>

			</b:comments>
			<b:trackbacks trackbackCount="0" trackbackURL="">

			</b:trackbacks>
		</b:entry>
	</b:entries>
</b:blog>