<?xml version="1.0" encoding="UTF-8"?>
<?xml-stylesheet type="text/xsl" href="/main.xsl"?>
<b:blog xmlns="http://www.w3.org/1999/xhtml" xmlns:b="http://blog.othree.net"  xmlns:xsi="http://www.w3.org/2001/XMLSchema-instance" xsi:schemaLocation="http://blog.othree.net http://blog.othree.net/blooog.xsd">
	<b:blogTitle>O3noBLOG</b:blogTitle>
	<b:blogDescription></b:blogDescription>
	<b:entries>
		<b:entriesMeta>
			<b:listType>s</b:listType>
			<b:listData listID="000683" baseName="jquery-16">jQuery 1.6</b:listData>

			<b:previous>
				<b:mTitle>Eye-Fi Direct Mode</b:mTitle>
				<b:mDate>2011-04-22</b:mDate>
				<b:mBase>eye-fi-direct-mode</b:mBase>
			</b:previous>


			<b:next>
				<b:mTitle>jQuery 1.6.1</b:mTitle>
				<b:mDate>2011-05-13</b:mDate>
				<b:mBase>jquery-161</b:mBase>
			</b:next>

		</b:entriesMeta>
		<b:entry entryID="000683" baseName="jquery-16">
			<b:author>
				<b:authorName>othree</b:authorName>
				<b:authorEmail>othree@gmail.com</b:authorEmail>
				<b:authorUrl></b:authorUrl>
			</b:author>
			<b:datetime>
				<b:date>2011-05-07</b:date>
				<b:time>11:33:24</b:time>
			</b:datetime>
			<b:category>script</b:category>

			<b:CommentsAccepted>0</b:CommentsAccepted>


			<b:PingsAccepted>0</b:PingsAccepted>

			<b:title>jQuery 1.6</b:title>
			<b:content>
				<b:summary>jQuery 1.6 前兩天剛出來，改變不少，其中我覺得影響最大的就是 attr() 和 prop() 這兩個東西了，attr 變成完全是依照 HTML 原始碼的內容回傳東西，所以像是 checkbox 標籤的 checked 屬性： &lt;input type="checkbox" checked&gt; 以前用 attr 會傳回 true，但是現在會傳回空字串，因為他沒有設定內容，如果要向以前一樣使用，變成要改用 prop 來純取屬性了，我用 jsFiddle 作了個簡單範例給大家看看： 順便趁機問問大家意見，attribute 和 properties 同時出現時，中文翻譯要怎樣區別呢？...</b:summary>
				<b:mainContent><p><a href="http://blog.jquery.com/2011/05/03/jquery-16-released/">jQuery 1.6</a> 前兩天剛出來，改變不少，其中我覺得影響最大的就是 <a href="http://api.jquery.com/attr/">attr()</a> 和 <a href="http://api.jquery.com/prop/">prop()</a> 這兩個東西了，attr 變成完全是依照 HTML 原始碼的內容回傳東西，所以像是 checkbox 標籤的 checked 屬性：</p>

<pre><code>&lt;input type="checkbox" checked&gt;
</code></pre>

<p>以前用 attr 會傳回 true，但是現在會傳回空字串，因為他沒有設定內容，如果要向以前一樣使用，變成要改用 prop 來純取屬性了，我用 jsFiddle 作了個簡單範例給大家看看：</p>

<iframe style="width: 500px; height: 300px" src="http://jsfiddle.net/othree/YQAL8/embedded/"></iframe>

<p>順便趁機問問大家意見，attribute 和 properties 同時出現時，中文翻譯要怎樣區別呢？</p>
</b:mainContent>
				<b:extendContent>
</b:extendContent>
			</b:content>
			<b:comments commentCount="3">

				<b:comment commentID="113775" entryID="000683">
					<b:author>
						<b:authorName>phantoms</b:authorName>
						<b:authorEmail></b:authorEmail>
						<b:authorUrl></b:authorUrl>
					</b:author>
					<b:datetime>
						<b:date>2011-05-07</b:date>
						<b:time>20:31:52</b:time>
					</b:datetime>
					<b:content>
						<b:mainContent><p>attribute = 屬性
property = 特性</p>
</b:mainContent>
					</b:content>
				</b:comment>

				<b:comment commentID="113969" entryID="000683">
					<b:author>
						<b:authorName>OOO</b:authorName>
						<b:authorEmail>othree@gmail.com</b:authorEmail>
						<b:authorUrl>http://blog.othree.net</b:authorUrl>
					</b:author>
					<b:datetime>
						<b:date>2011-05-13</b:date>
						<b:time>12:05:59</b:time>
					</b:datetime>
					<b:content>
						<b:mainContent><p>@phantoms 感謝你的建議:)</p>
</b:mainContent>
					</b:content>
				</b:comment>

				<b:comment commentID="113972" entryID="000683">
					<b:author>
						<b:authorName>Anonymous</b:authorName>
						<b:authorEmail></b:authorEmail>
						<b:authorUrl></b:authorUrl>
					</b:author>
					<b:datetime>
						<b:date>2011-05-13</b:date>
						<b:time>12:42:30</b:time>
					</b:datetime>
					<b:content>
						<b:mainContent><p>怪了，本來打中文怎麼會不見&#8230;
attribute=屬性 shuxing
property=特性 texing</p>
</b:mainContent>
					</b:content>
				</b:comment>

			</b:comments>
			<b:trackbacks trackbackCount="0" trackbackURL="https://othree.net/mt/mt-tb.cgi/682">

			</b:trackbacks>
		</b:entry>
	</b:entries>
</b:blog>