<?xml version="1.0" encoding="UTF-8"?>
<?xml-stylesheet type="text/xsl" href="/main.xsl"?>
<b:blog xmlns="http://www.w3.org/1999/xhtml" xmlns:b="http://blog.othree.net"  xmlns:xsi="http://www.w3.org/2001/XMLSchema-instance" xsi:schemaLocation="http://blog.othree.net http://blog.othree.net/blooog.xsd">
	<b:blogTitle>O3noBLOG</b:blogTitle>
	<b:blogDescription></b:blogDescription>
	<b:entries>
		<b:entriesMeta>
			<b:listType>s</b:listType>
			<b:listData listID="000372" baseName="hard-to-follow-w3c">完全遵照W3C標準？</b:listData>

			<b:previous>
				<b:mTitle>Firefox 3 將成為資訊中間人</b:mTitle>
				<b:mDate>2007-01-07</b:mDate>
				<b:mBase>firefox-3-as-information-broker</b:mBase>
			</b:previous>


			<b:next>
				<b:mTitle>WebKit支援CSS3的box-shadow了</b:mTitle>
				<b:mDate>2007-01-08</b:mDate>
				<b:mBase>webkit-support-css3-box-shadow</b:mBase>
			</b:next>

		</b:entriesMeta>
		<b:entry entryID="000372" baseName="hard-to-follow-w3c">
			<b:author>
				<b:authorName>othree</b:authorName>
				<b:authorEmail>othree@gmail.com</b:authorEmail>
				<b:authorUrl></b:authorUrl>
			</b:author>
			<b:datetime>
				<b:date>2007-01-08</b:date>
				<b:time>01:32:04</b:time>
			</b:datetime>
			<b:category>web</b:category>

			<b:CommentsAccepted>1</b:CommentsAccepted>



			<b:PingsAccepted>0</b:PingsAccepted>

			<b:title>完全遵照W3C標準？</b:title>
			<b:content>
				<b:summary>這又是一個似乎要屈服在現實考量下的問題了，在現今的網路環境下，要完全遵照W3C的標準及建議來建製網頁其實還蠻有困難以及不方便的，除了CSS 3還要制定很久、IE對現有CSS的bug，因此有不少人用了CSS hack，當然大部分都不會通過CSS語法檢查，另外網頁表單已經不敷使用了，所以有了Web Forms 2.0（不是W3C制定的，不過W3C有想和XForms整合到XHTML），裡面像是required的屬性值就很有用，但是加上去就過不了HTML檢查，還有要用object取代embed、img兩種標籤，卡在IE支援度問題，一直推展不起來。 會想寫這篇是因為最近很想用一些Web Forms 2.0的東西，加上Peter-Paul Koch是站在不需要通過檢查那派的，至於我，以前是很守標準的那派，不過這次改版時就已經有一些理念不像以前那樣堅持了，現在則覺得好像快要大徹大悟了XD。 其他：我到現在還看不懂XForms的內容。...</b:summary>
				<b:mainContent><p>這又是一個似乎要屈服在現實考量下的問題了，在現今的網路環境下，要完全遵照W3C的標準及建議來建製網頁其實還蠻有困難以及不方便的，除了<a href="http://www.w3.org/Style/CSS/current-work"><span class="caps">CSS</span> 3</a>還要制定很久、IE對現有CSS的bug，因此有不少人用了<a href="http://centricle.com/ref/css/filters/"><span class="caps">CSS </span>hack</a>，當然大部分都不會通過<a href="http://jigsaw.w3.org/css-validator/"><span class="caps">CSS</span>語法檢查</a>，另外網頁表單已經不敷使用了，所以有了<a href="http://www.whatwg.org/specs/web-forms/current-work/">Web Forms 2.0</a>（不是W3C制定的，不過W3C有想和<a href="http://www.w3.org/MarkUp/Forms/">XForms</a>整合到XHTML），裡面像是required的屬性值就很有用，但是加上去就過不了<a href="http://validator.w3.org/"><span class="caps">HTML</span>檢查</a>，還有要用<a href="http://www.w3.org/TR/html4/struct/objects.html#edef-OBJECT">object</a>取代embed、img兩種標籤，卡在IE支援度問題，一直推展不起來。</p>

<p>會想寫這篇是因為最近很想用一些Web Forms 2.0的東西，加上Peter-Paul Koch是站在不需要通過檢查那派的，至於我，以前是很守標準的那派，不過這次改版時就已經有一些理念不像以前那樣堅持了，現在則覺得好像快要大徹大悟了XD。</p>

<p>其他：我到現在還看不懂XForms的內容。</p></b:mainContent>
				<b:extendContent></b:extendContent>
			</b:content>
			<b:comments commentCount="0">

			</b:comments>
			<b:trackbacks trackbackCount="0" trackbackURL="https://othree.net/mt/mt-tb.cgi/371">

			</b:trackbacks>
		</b:entry>
	</b:entries>
</b:blog>