<?xml version="1.0" encoding="UTF-8"?>
<?xml-stylesheet type="text/xsl" href="/main.xsl"?>
<b:blog xmlns="http://www.w3.org/1999/xhtml" xmlns:b="http://blog.othree.net"  xmlns:xsi="http://www.w3.org/2001/XMLSchema-instance" xsi:schemaLocation="http://blog.othree.net http://blog.othree.net/blooog.xsd">
	<b:blogTitle>O3noBLOG</b:blogTitle>
	<b:blogDescription></b:blogDescription>
	<b:entries>
		<b:entriesMeta>
			<b:listType>s</b:listType>
			<b:listData listID="000185" baseName="i-hate-publish-late">我討厭出書不準時</b:listData>

			<b:previous>
				<b:mTitle>CSS Hacks and Filters : Making Cascading Stylesheets Work</b:mTitle>
				<b:mDate>2005-06-14</b:mDate>
				<b:mBase>css-hacks-and-filters</b:mBase>
			</b:previous>


			<b:next>
				<b:mTitle>電腦繪圖期末報告</b:mTitle>
				<b:mDate>2005-06-18</b:mDate>
				<b:mBase>opengl-project</b:mBase>
			</b:next>

		</b:entriesMeta>
		<b:entry entryID="000185" baseName="i-hate-publish-late">
			<b:author>
				<b:authorName>othree</b:authorName>
				<b:authorEmail>othree@gmail.com</b:authorEmail>
				<b:authorUrl></b:authorUrl>
			</b:author>
			<b:datetime>
				<b:date>2005-06-18</b:date>
				<b:time>18:52:15</b:time>
			</b:datetime>
			<b:category>diary</b:category>

			<b:CommentsAccepted>1</b:CommentsAccepted>



			<b:PingsAccepted>0</b:PingsAccepted>

			<b:title>我討厭出書不準時</b:title>
			<b:content>
				<b:summary>這兩天為了買本數位時代跑來跑去，一直到昨天晚上才買到，讓我蠻不高興的（這種天氣大家也知道），另外就是尖端出的灌籃高手完全版也是，一二集都遲個兩三天，也是讓我一直白跑，不過昨天的第三集意外的很準時，我本來是打定要過兩天在去買的，要不是要為了買數位時代才會順便去看看的。...</b:summary>
				<b:mainContent><p>這兩天為了買本<a href="http://www2.bnext.com.tw/mag/2005_06_15/2005_06_15_3338.html">數位時代</a>跑來跑去，一直到昨天晚上才買到，讓我蠻不高興的（這種天氣大家也知道），另外就是尖端出的<a href="http://www.spp.com.tw/htm/other/slumdunk/campaign.html">灌籃高手完全版</a>也是，一二集都遲個兩三天，也是讓我一直白跑，不過昨天的第三集意外的很準時，我本來是打定要過兩天在去買的，要不是要為了買數位時代才會順便去看看的。</p></b:mainContent>
				<b:extendContent></b:extendContent>
			</b:content>
			<b:comments commentCount="0">

			</b:comments>
			<b:trackbacks trackbackCount="0" trackbackURL="http://othree.net/mt/mt-tb.cgi/184">

			</b:trackbacks>
		</b:entry>
	</b:entries>
</b:blog>