<?xml version="1.0" encoding="UTF-8"?>
<?xml-stylesheet type="text/xsl" href="/main.xsl"?>
<b:blog xmlns="http://www.w3.org/1999/xhtml" xmlns:b="http://blog.othree.net"  xmlns:xsi="http://www.w3.org/2001/XMLSchema-instance" xsi:schemaLocation="http://blog.othree.net http://blog.othree.net/blooog.xsd">
	<b:blogTitle>O3noBLOG</b:blogTitle>
	<b:blogDescription></b:blogDescription>
	<b:entries>
		<b:entriesMeta>
			<b:listType>s</b:listType>
			<b:listData listID="000707" baseName="coscup-2012-slides">COSCUP 2012 slides</b:listData>

			<b:previous>
				<b:mTitle>鍵盤攻頂這檔事</b:mTitle>
				<b:mDate>2012-08-13</b:mDate>
				<b:mBase>top-keyboard</b:mBase>
			</b:previous>


			<b:next>
				<b:mTitle>jQuery.Deferred.pipe</b:mTitle>
				<b:mDate>2012-08-21</b:mDate>
				<b:mBase>jquery-deferred-pipe</b:mBase>
			</b:next>

		</b:entriesMeta>
		<b:entry entryID="000707" baseName="coscup-2012-slides">
			<b:author>
				<b:authorName>othree</b:authorName>
				<b:authorEmail>othree@gmail.com</b:authorEmail>
				<b:authorUrl></b:authorUrl>
			</b:author>
			<b:datetime>
				<b:date>2012-08-20</b:date>
				<b:time>00:51:42</b:time>
			</b:datetime>
			<b:category>script</b:category>

			<b:CommentsAccepted>0</b:CommentsAccepted>


			<b:PingsAccepted>0</b:PingsAccepted>

			<b:title>COSCUP 2012 slides</b:title>
			<b:content>
				<b:summary> /* A_A */ /* A_A */ 說好的 deferred.pipe 文章應該明天就可以貼出了～...</b:summary>
				<b:mainContent><p>
<script async="async" class="speakerdeck-embed" data-id="502fb1b39a533c000203951d" data-ratio="1.3333333333333333" src="//speakerdeck.com/assets/embed.js">/* A_A */</script>
</p>

<p>
<script async="async" class="speakerdeck-embed" data-id="503108129c9652000203d80a" data-ratio="1.3333333333333333" src="//speakerdeck.com/assets/embed.js">/* A_A */</script>
</p>

<p>說好的 deferred.pipe 文章應該明天就可以貼出了～</p>
</b:mainContent>
				<b:extendContent>
</b:extendContent>
			</b:content>
			<b:comments commentCount="1">

				<b:comment commentID="248568" entryID="000707">
					<b:author>
						<b:authorName>jocosn</b:authorName>
						<b:authorEmail>jocosn@yahoo.com.tw</b:authorEmail>
						<b:authorUrl></b:authorUrl>
					</b:author>
					<b:datetime>
						<b:date>2012-08-30</b:date>
						<b:time>04:32:17</b:time>
					</b:datetime>
					<b:content>
						<b:mainContent><p>這投影片講解的很詳細，鼓掌叫好。希望&amp;期待一系列 jQuery 或其它framework 的簡報。</p>
</b:mainContent>
					</b:content>
				</b:comment>

			</b:comments>
			<b:trackbacks trackbackCount="0" trackbackURL="https://othree.net/mt/mt-tb.cgi/705">

			</b:trackbacks>
		</b:entry>
	</b:entries>
</b:blog>