<?xml version="1.0" encoding="UTF-8"?>
<?xml-stylesheet type="text/xsl" href="/main.xsl"?>
<b:blog xmlns="http://www.w3.org/1999/xhtml" xmlns:b="http://blog.othree.net"  xmlns:xsi="http://www.w3.org/2001/XMLSchema-instance" xsi:schemaLocation="http://blog.othree.net http://blog.othree.net/blooog.xsd">
	<b:blogTitle>O3noBLOG</b:blogTitle>
	<b:blogDescription></b:blogDescription>
	<b:entries>
		<b:entriesMeta>
			<b:listType>s</b:listType>
			<b:listData listID="000016" baseName="catch-cold-day-4">感冒第四天</b:listData>

			<b:previous>
				<b:mTitle>用OBJECT標籤來放圖片</b:mTitle>
				<b:mDate>2003-12-17</b:mDate>
				<b:mBase>image-in-object-tag</b:mBase>
			</b:previous>


			<b:next>
				<b:mTitle>mod_perl 跑 MT</b:mTitle>
				<b:mDate>2003-12-19</b:mDate>
				<b:mBase>run-mt-under-mod-perl</b:mBase>
			</b:next>

		</b:entriesMeta>
		<b:entry entryID="000016" baseName="catch-cold-day-4">
			<b:author>
				<b:authorName>othree</b:authorName>
				<b:authorEmail>othree@gmail.com</b:authorEmail>
				<b:authorUrl></b:authorUrl>
			</b:author>
			<b:datetime>
				<b:date>2003-12-18</b:date>
				<b:time>09:33:51</b:time>
			</b:datetime>
			<b:category>diary</b:category>

			<b:CommentsAccepted>1</b:CommentsAccepted>



			<b:PingsAccepted>0</b:PingsAccepted>

			<b:title>感冒第四天</b:title>
			<b:content>
				<b:summary>等下總算能去看醫生了。第一天只是喉嚨痛，第二天開始咳嗽，加上扁條線好像發炎腫起來，第三天，也就是昨天，大概是這次感冒最辛苦的一天了，喉嚨雖然不痛了，咳嗽狀況也好多了，不過因為前一天咳太多，腹肌已經受傷，只要一咳就會很痛，接著頭也漸漸開始不舒服，果然晚上好像發燒了，關節也怪怪的。還好今天早上起來狀況好很多，不過腹肌...，現在連擤鼻涕都會痛Q_Q！ 題外話，昨天去補習班時，門口有人在量體溫，我很成功的沒發燒進去了，結果好像上課上一上開始發燒^^b，後來回家才看到新聞說又有人感染SARS了。...</b:summary>
				<b:mainContent><p>等下總算能去看醫生了。第一天只是喉嚨痛，第二天開始咳嗽，加上扁條線好像發炎腫起來，第三天，也就是昨天，大概是這次感冒最辛苦的一天了，喉嚨雖然不痛了，咳嗽狀況也好多了，不過因為前一天咳太多，腹肌已經受傷，只要一咳就會很痛，接著頭也漸漸開始不舒服，果然晚上好像發燒了，關節也怪怪的。還好今天早上起來狀況好很多，不過腹肌...，現在連擤鼻涕都會痛Q_Q！</p>

<p>題外話，昨天去補習班時，門口有人在量體溫，我很成功的沒發燒進去了，結果好像上課上一上開始發燒^^b，後來回家才看到新聞說又有人感染SARS了。</p></b:mainContent>
				<b:extendContent></b:extendContent>
			</b:content>
			<b:comments commentCount="0">

			</b:comments>
			<b:trackbacks trackbackCount="0" trackbackURL="https://othree.net/mt/mt-tb.cgi/128">

			</b:trackbacks>
		</b:entry>
	</b:entries>
</b:blog>