<?xml version="1.0" encoding="UTF-8"?>
<?xml-stylesheet type="text/xsl" href="/main.xsl"?>
<b:blog xmlns="http://www.w3.org/1999/xhtml" xmlns:b="http://blog.othree.net"  xmlns:xsi="http://www.w3.org/2001/XMLSchema-instance" xsi:schemaLocation="http://blog.othree.net http://blog.othree.net/blooog.xsd">
	<b:blogTitle>O3noBLOG</b:blogTitle>
	<b:blogDescription></b:blogDescription>
	<b:entries>
		<b:entriesMeta>
			<b:listType>s</b:listType>
			<b:listData listID="000674" baseName="html5-developer-edition">HTML5 Web Developer Edition</b:listData>

			<b:previous>
				<b:mTitle>偵測 Clear Type</b:mTitle>
				<b:mDate>2011-03-04</b:mDate>
				<b:mBase>detect-clear-type</b:mBase>
			</b:previous>


			<b:next>
				<b:mTitle>RevCanonical and rel-shortlink</b:mTitle>
				<b:mDate>2011-03-05</b:mDate>
				<b:mBase>revcanonical-and-relshortlink</b:mBase>
			</b:next>

		</b:entriesMeta>
		<b:entry entryID="000674" baseName="html5-developer-edition">
			<b:author>
				<b:authorName>othree</b:authorName>
				<b:authorEmail>othree@gmail.com</b:authorEmail>
				<b:authorUrl></b:authorUrl>
			</b:author>
			<b:datetime>
				<b:date>2011-03-05</b:date>
				<b:time>16:19:36</b:time>
			</b:datetime>
			<b:category>css-html</b:category>

			<b:CommentsAccepted>1</b:CommentsAccepted>



			<b:PingsAccepted>0</b:PingsAccepted>

			<b:title>HTML5 Web Developer Edition</b:title>
			<b:content>
				<b:summary> HTML5 標準的文件 和以前的版本有些地方有很大的不同，像是標籤的語意說明比起以前就詳細很多，還會提出範例，另外也更詳細的規範了瀏覽器應該怎樣實作的細節，也因此整份文件的長度非常驚人，WHATWG 那邊有提供 A4 PDF 的版本 ，將近有 800 頁的內容，非常驚人， HTML 4 也才接近 400 頁而已，文字量則接近 3 倍，而這麼多的內容其實不是所有人都需要的，例如網頁設計師，它就不需要理解一些 API 的實作細節，他只要知道不同的標籤應該怎樣使用，怎樣編排網頁結構符合語義，因此 Ben Schwars 就做出了一份針對 Web Developer 的 HTML5 文件「HTML5 - Edition for Web Developers」，只保留了 Web Developer 需要的資訊，而且還整個把頁面樣式大改，不只是更漂亮而已，還針對可讀性下了不少 功夫 ，還有搜尋、單一章節的目錄等，閱讀的體驗實在是提昇非常多。 而一如往常的，W3C 那邊也有一份...</b:summary>
				<b:mainContent><p><a class="thumbnail" href="http://www.flickr.com/photos/othree/5498667619/" title="Flickr 上 othree 的 HTML5 -- Edition for Web Developers"><img src="//farm6.static.flickr.com/5171/5498667619_1817f41fba.jpg" width="500" height="475" alt="HTML5 -- Edition for Web Developers" /></a></p>

<p><a href="http://dev.w3.org/html5/spec/">HTML5 標準的文件</a> 和以前的版本有些地方有很大的不同，像是標籤的語意說明比起以前就詳細很多，還會提出範例，另外也更詳細的規範了瀏覽器應該怎樣實作的細節，也因此整份文件的長度非常驚人，WHATWG 那邊有提供 <a href="http://www.whatwg.org/specs/web-apps/current-work/html-a4.pdf">A4 PDF 的版本</a> ，將近有 800 頁的內容，非常驚人， <a href="http://www.w3.org/TR/html401/html40.pdf.gz">HTML 4</a> 也才接近 400 頁而已，文字量則接近 3 倍，而這麼多的內容其實不是所有人都需要的，例如網頁設計師，它就不需要理解一些 API 的實作細節，他只要知道不同的標籤應該怎樣使用，怎樣編排網頁結構符合語義，因此 <a href="http://germanforblack.com/">Ben Schwars</a> 就做出了一份針對 Web Developer 的 HTML5 文件「<a href="http://developers.whatwg.org/">HTML5 - Edition for Web Developers</a>」，只保留了 Web Developer 需要的資訊，而且還整個把頁面樣式大改，不只是更漂亮而已，還針對可讀性下了不少 <a href="http://www.germanforblack.com/articles/moving-towards-readable-w3c-specs">功夫</a> ，還有搜尋、單一章節的目錄等，閱讀的體驗實在是提昇非常多。</p>

<p>而一如往常的，W3C 那邊也有一份 <a href="http://dev.w3.org/html5/spec-author-view/">HTML5 Edition for Web Authors</a> ，兩份其實是同樣的文件，我在 Ben Schwars 的 <a href="http://www.slideshare.net/benschwarz/building-a-better-web">Building a better web</a> 這份投影片中看到的網址就是 W3C 這邊的，目前的關係大概也只是不同的更新版本吧，我剛發現時幾乎是只有配色不同，現在樣式兩邊就有些差異了，不過章節內容還是差不多，順序有些調動，喔對了，這份投影片第 14 頁還有個不錯 W3C 標誌。</p>

<p>最後要提的是 Ben Schwars 是自己主動建立了這份文件的，他在看 HTML5 標準後受不了，跑去 WHATWG IRC 說他要做這東西，編輯說 ok 後他就開始動手了，他也把這段 <a href="http://germanforblack.com/articles/taking-the-web-back">過程</a> 寫出來，呼籲大家盡量參與標準的發展，不要只是對 W3C 有意見卻不參與不貢獻。</p>
</b:mainContent>
				<b:extendContent>
</b:extendContent>
			</b:content>
			<b:comments commentCount="0">

			</b:comments>
			<b:trackbacks trackbackCount="0" trackbackURL="https://othree.net/mt/mt-tb.cgi/673">

			</b:trackbacks>
		</b:entry>
	</b:entries>
</b:blog>